[
    {
        "author": "释省回",
        "dynasty": "宋",
        "type": "诗",
        "rhythmic": "",
        "title": "偈",
        "preface": "",
        "paragraphs": [
            "南番人泛船，塞北人摇舻。",
            "波斯入大唐，须弥山作舞。"
        ],
        "notes": "",
        "id": "0e5576dd7683b27320c9c0497c47785f"
    },
    {
        "author": "释省回",
        "dynasty": "宋",
        "type": "诗",
        "rhythmic": "",
        "title": "辞众偈",
        "preface": "",
        "paragraphs": [
            "九十二光阴，分明对众说。",
            "远洞散寒云，幽窗度残月。"
        ],
        "notes": "",
        "id": "f922f78481878c670dc99e6ea307846f"
    }
]