[
    {
        "author": "毕仲愈",
        "dynasty": "宋",
        "type": "诗",
        "rhythmic": "",
        "title": "句  其一",
        "preface": "",
        "paragraphs": [
            "徘徊幽兴尽。"
        ],
        "notes": "",
        "id": "6df5c2da0c1d806ae6e1fb23a2ed00b9"
    },
    {
        "author": "毕仲愈",
        "dynasty": "宋",
        "type": "诗",
        "rhythmic": "",
        "title": "句  其二",
        "preface": "",
        "paragraphs": [
            "已招明月移歌扇，更倩春风试舞腰。"
        ],
        "notes": "",
        "id": "3274b6c67a452208d1c72cfae8d3c2bc"
    },
    {
        "author": "毕仲愈",
        "dynasty": "宋",
        "type": "诗",
        "rhythmic": "",
        "title": "句  其三",
        "preface": "",
        "paragraphs": [
            "明灯数点林中见，横笛一声烟外闻。"
        ],
        "notes": "",
        "id": "fae0d6b59384f906387b1eb3cbdd43be"
    }
]